django_mptt_admin/__init__.py
django_mptt_admin/admin.py
django_mptt_admin/django_mptt_admin_mixin.py
django_mptt_admin/tree_change_list.py
django_mptt_admin/util.py
django_mptt_admin/locale/ca/LC_MESSAGES/django.mo
django_mptt_admin/locale/ca/LC_MESSAGES/django.po
django_mptt_admin/locale/ca/LC_MESSAGES/djangojs.mo
django_mptt_admin/locale/ca/LC_MESSAGES/djangojs.po
django_mptt_admin/locale/de/LC_MESSAGES/django.mo
django_mptt_admin/locale/de/LC_MESSAGES/django.po
django_mptt_admin/locale/de/LC_MESSAGES/djangojs.mo
django_mptt_admin/locale/de/LC_MESSAGES/djangojs.po
django_mptt_admin/locale/es/LC_MESSAGES/django.mo
django_mptt_admin/locale/es/LC_MESSAGES/django.po
django_mptt_admin/locale/es/LC_MESSAGES/djangojs.mo
django_mptt_admin/locale/es/LC_MESSAGES/djangojs.po
django_mptt_admin/locale/fr/LC_MESSAGES/django.mo
django_mptt_admin/locale/fr/LC_MESSAGES/django.po
django_mptt_admin/locale/fr/LC_MESSAGES/djangojs.mo
django_mptt_admin/locale/fr/LC_MESSAGES/djangojs.po
django_mptt_admin/locale/he/LC_MESSAGES/django.mo
django_mptt_admin/locale/he/LC_MESSAGES/django.po
django_mptt_admin/locale/he/LC_MESSAGES/djangojs.mo
django_mptt_admin/locale/he/LC_MESSAGES/djangojs.po
django_mptt_admin/locale/hu/LC_MESSAGES/django.mo
django_mptt_admin/locale/hu/LC_MESSAGES/django.po
django_mptt_admin/locale/hu/LC_MESSAGES/djangojs.mo
django_mptt_admin/locale/hu/LC_MESSAGES/djangojs.po
django_mptt_admin/locale/pl/LC_MESSAGES/django.mo
django_mptt_admin/locale/pl/LC_MESSAGES/django.po
django_mptt_admin/locale/pl/LC_MESSAGES/djangojs.mo
django_mptt_admin/locale/pl/LC_MESSAGES/djangojs.po
django_mptt_admin/locale/ru/LC_MESSAGES/django.mo
django_mptt_admin/locale/ru/LC_MESSAGES/django.po
django_mptt_admin/locale/ru/LC_MESSAGES/djangojs.mo
django_mptt_admin/locale/ru/LC_MESSAGES/djangojs.po
django_mptt_admin/locale/tr/LC_MESSAGES/django.mo
django_mptt_admin/locale/tr/LC_MESSAGES/django.po
django_mptt_admin/locale/tr/LC_MESSAGES/djangojs.mo
django_mptt_admin-2.7.1.dist-info/LICENSE.rst
django_mptt_admin-2.7.1.dist-info/METADATA
django_mptt_admin-2.7.1.dist-info/WHEEL
django_mptt_admin-2.7.1.dist-info/top_level.txt
django_mptt_admin-2.7.1.dist-info/RECORD
