Metadata-Version: 2.1
Name: django-mptt-admin
Version: 2.7.1
Summary: Django-mptt-admin provides a nice Django Admin interface for Mptt models
Home-page: https://github.com/mbraak/django-mptt-admin
Author: Marco Braak
Author-email: marco.braak@planet.nl
License: Apache License, Version 2.0
Classifier: Development Status :: 5 - Production/Stable
Classifier: Framework :: Django
Classifier: Framework :: Django :: 4.2
Classifier: Framework :: Django :: 5.0
Classifier: Framework :: Django :: 5.1
Classifier: Intended Audience :: Developers
Classifier: License :: OSI Approved :: Apache Software License
Classifier: Programming Language :: Python :: 3.8
Classifier: Programming Language :: Python :: 3.9
Classifier: Programming Language :: Python :: 3.10
Classifier: Programming Language :: Python :: 3.11
Classifier: Programming Language :: Python :: 3.12
Classifier: Programming Language :: Python :: Implementation :: CPython
License-File: LICENSE.rst
Requires-Dist: django-mptt
